sudokuku/__init__.py
sudokuku/coordinate_calculator.py
sudokuku/field_status.py
sudokuku/manager.py
sudokuku/sudokuwrapped.py
sudokuku-0.4.0.dist-info/LICENSE
sudokuku-0.4.0.dist-info/METADATA
sudokuku-0.4.0.dist-info/WHEEL
sudokuku-0.4.0.dist-info/top_level.txt
sudokuku-0.4.0.dist-info/RECORD
