Metadata-Version: 2.1
Name: sudokuku
Version: 0.4.0
Summary: A package for solving sudokus
Home-page: https://github.com/jonasstrube/sudokuku
Author: Jonas Strube
Classifier: Programming Language :: Python :: 3
Classifier: License :: OSI Approved :: MIT License
Classifier: Operating System :: OS Independent
Requires-Python: >=3.9
License-File: LICENSE
